pysetting/__init__.py
pysetting/pysetting.py
pysetting-0.0.6.dist-info/LICENSE
pysetting-0.0.6.dist-info/METADATA
pysetting-0.0.6.dist-info/WHEEL
pysetting-0.0.6.dist-info/top_level.txt
pysetting-0.0.6.dist-info/RECORD
