Metadata-Version: 2.1
Name: pysetting
Version: 0.0.6
Summary: A python library for parsing and storing settings and configurations.
Home-page: https://github.com/shivanandvp/pysetting
Download-URL: https://pypi.org/project/pysetting/
Author: shivanandvp
Author-email: shivanandvp.oss@gmail.com
Project-URL: Documentation, https://github.com/shivanandvp/pysetting/
Project-URL: Source, https://github.com/shivanandvp/pysetting
Project-URL: Tracker, https://github.com/shivanandvp/pysetting/issues
Classifier: Programming Language :: Python :: 3.11
Classifier: Development Status :: 4 - Beta
Classifier: License :: OSI Approved :: Mozilla Public License 2.0 (MPL 2.0)
Classifier: Operating System :: POSIX :: Linux
Classifier: Intended Audience :: Developers
Classifier: Intended Audience :: System Administrators
Classifier: Natural Language :: English
Classifier: Typing :: Typed
Classifier: Topic :: Software Development :: Libraries :: Python Modules
Classifier: Topic :: System :: Systems Administration
Classifier: Topic :: Utilities
Requires-Python: >=3.10
License-File: LICENSE
